muopdb_python_client/__init__.py
muopdb_python_client/client.py
muopdb_python_client/exceptions.py
muopdb_python_client/utils.py
muopdb_python_client/vectorizer.py
muopdb_python_client/protos/__init__.py
muopdb_python_client/protos/muopdb.proto
muopdb_python_client/protos/muopdb_pb2.py
muopdb_python_client/protos/muopdb_pb2_grpc.py
muopdb_python_client-0.0.9.dist-info/licenses/LICENSE
muopdb_python_client-0.0.9.dist-info/METADATA
muopdb_python_client-0.0.9.dist-info/WHEEL
muopdb_python_client-0.0.9.dist-info/top_level.txt
muopdb_python_client-0.0.9.dist-info/RECORD
