Metadata-Version: 2.4
Name: muopdb_python_client
Version: 0.0.9
Summary: Python client for MuopDB
Author-email: Tech Care <info@techcarecoaching.com>
Maintainer-email: Ginny Khue Dang <khuedang1021@gmail.com>, Ruby Bui <rubybui.swe@gmail.com>
License-Expression: MIT
Project-URL: Homepage, https://github.com/chauvm/muopdb_python_client
Project-URL: Repository, https://github.com/chauvm/muopdb_python_client.git
Project-URL: Bug Tracker, https://github.com/chauvm/muopdb_python_client/issues
Classifier: Development Status :: 3 - Alpha
Classifier: Intended Audience :: Developers
Classifier: Programming Language :: Python :: 3
Classifier: Programming Language :: Python :: 3.7
Classifier: Programming Language :: Python :: 3.8
Classifier: Programming Language :: Python :: 3.9
Classifier: Programming Language :: Python :: 3.10
Requires-Python: <3.13,>=3.7
License-File: LICENSE
Requires-Dist: grpcio>=1.59.0
Requires-Dist: grpcio-tools>=1.59.0
Requires-Dist: protobuf>=4.25.1
Requires-Dist: openai
Requires-Dist: google-genai
Requires-Dist: voyageai
Requires-Dist: ollama
Requires-Dist: dotenv
Requires-Dist: pytest-order>=1.3.0
Requires-Dist: pytest>=8.3.5
Requires-Dist: pytest-cov>=6.0.0
Requires-Dist: sentence-transformers>=2.2.2
Requires-Dist: transformers>=4.30.0
Requires-Dist: torch>=2.0.0
Requires-Dist: requests>=2.25.0
Provides-Extra: dev
Requires-Dist: pytest>=6.0; extra == "dev"
Requires-Dist: pytest-cov; extra == "dev"
Requires-Dist: black; extra == "dev"
Requires-Dist: flake8; extra == "dev"
Requires-Dist: mypy; extra == "dev"
Dynamic: license-file
